{
  "name" : "Dept",
  "preName" : "",
  "comment" : null,
  "templateGroupName" : "Default",
  "fullColumn" : [ {
    "name" : "deptno",
    "comment" : null,
    "type" : null,
    "shortType" : null,
    "custom" : false,
    "ext" : { }
  }, {
    "name" : "dname",
    "comment" : null,
    "type" : null,
    "shortType" : null,
    "custom" : false,
    "ext" : { }
  }, {
    "name" : "loc",
    "comment" : null,
    "type" : null,
    "shortType" : null,
    "custom" : false,
    "ext" : { }
  } ],
  "pkColumn" : null,
  "otherColumn" : null,
  "savePackageName" : "com.bjpowernode.style",
  "savePath" : "./ch07-mybatis-generator-test/src/main/java/com/bjpowernode/style",
  "saveModelName" : "ch07-mybatis-generator-test"
}